godoo_cli/__about__.py
godoo_cli/__init__.py
godoo_cli/__main__.py
godoo_cli/cli.py
godoo_cli/cli_common.py
godoo_cli/commands/__init__.py
godoo_cli/commands/config.py
godoo_cli/commands/source_get.py
godoo_cli/commands/backup/__init__.py
godoo_cli/commands/backup/cli.py
godoo_cli/commands/backup/dump.py
godoo_cli/commands/backup/load.py
godoo_cli/commands/backup/pull.py
godoo_cli/commands/backup/util.py
godoo_cli/commands/db/__init__.py
godoo_cli/commands/db/cli.py
godoo_cli/commands/db/passwords.py
godoo_cli/commands/db/query.py
godoo_cli/commands/odoo_bin/__init__.py
godoo_cli/commands/odoo_bin/bootstrap.py
godoo_cli/commands/odoo_bin/cli_generate.py
godoo_cli/commands/odoo_bin/launch.py
godoo_cli/commands/odoo_bin/shell.py
godoo_cli/commands/odoo_bin/godoo_test/__init__.py
godoo_cli/commands/odoo_bin/godoo_test/cli.py
godoo_cli/commands/odoo_bin/godoo_test/test_load_data.py
godoo_cli/commands/odoo_bin/godoo_test/test_run.py
godoo_cli/commands/odoo_bin/shell_scripts/odoo_banner.py
godoo_cli/commands/rpc/__init__.py
godoo_cli/commands/rpc/cli.py
godoo_cli/commands/rpc/config_parameters.py
godoo_cli/commands/rpc/importer.py
godoo_cli/commands/rpc/modules.py
godoo_cli/commands/rpc/translations.py
godoo_cli/git/__init__.py
godoo_cli/git/git_odoo.py
godoo_cli/git/git_odoo_addons.py
godoo_cli/git/git_repo.py
godoo_cli/git/git_url.py
godoo_cli/git/zip_download.py
godoo_cli/helpers/__init__.py
godoo_cli/helpers/cli.py
godoo_cli/helpers/modules_git.py
godoo_cli/helpers/modules_py.py
godoo_cli/helpers/odoo_files.py
godoo_cli/helpers/odoo_manifest.py
godoo_cli/helpers/pip.py
godoo_cli/helpers/system.py
godoo_cli/models/__init__.py
godoo_cli/models/db_connection.py
godoo_cli/models/godoo_models.py
godoo_cli/models/godoo_modules.py
godoo_cli-0.15.1.dist-info/METADATA
godoo_cli-0.15.1.dist-info/WHEEL
godoo_cli-0.15.1.dist-info/entry_points.txt
godoo_cli-0.15.1.dist-info/licenses/LICENSE
godoo_cli-0.15.1.dist-info/RECORD
