Metadata-Version: 2.4
Name: gOdoo-cli
Version: 0.15.1
Summary: Wrapper around Odoo-Bin with some convinience RPC functions.
Project-URL: repository, https://github.com/OpenJKSoftware/gOdoo
Author-email: Joshua Kreuder <Joshua_Kreuder@outlook.com>
License: LGPL-3.0-only
License-File: LICENSE
Keywords: devcontainer,godoo,odoo
Requires-Python: >=3.9
Requires-Dist: gitpython>=3.1.27
Requires-Dist: godoo-rpc>=0.1.4
Requires-Dist: openupgradelib>=3.3.4
Requires-Dist: passlib>=1.7.3
Requires-Dist: psycopg2>=2.7.7
Requires-Dist: python-dotenv>=0.20.0
Requires-Dist: ruamel-yaml>=0.17.21
Requires-Dist: typer-common-functions>=0.1.0
Requires-Dist: typer>=0.9.0
Provides-Extra: odoo-dev
Requires-Dist: debugpy>=1.6.0; extra == 'odoo-dev'
Requires-Dist: inotify>=0.2.10; extra == 'odoo-dev'
Requires-Dist: ipdb>=0.13.9; extra == 'odoo-dev'
Requires-Dist: pre-commit>=4.0.0; extra == 'odoo-dev'
Requires-Dist: py-spy>=0.3.11; extra == 'odoo-dev'
Requires-Dist: pydevd-odoo>=1.2.1; extra == 'odoo-dev'
Requires-Dist: pylint-odoo>=9.3.2; extra == 'odoo-dev'
Requires-Dist: rope>=0.23.0; extra == 'odoo-dev'
Requires-Dist: watchdog>=2.1.7; extra == 'odoo-dev'
